{
  "photos": [
    {
      "id": 1,
      "url": "http://source.unsplash.com/random/1",
      "user": {
        "name": "hilton"
      }
    },
    {
      "id": 2,
      "url": "http://source.unsplash.com/random/2",
      "user": {
        "name": "cardi B"
      }
    },
    {
      "id": 3,
      "url": "http://source.unsplash.com/random/3",
      "user": {
        "name": "hilton"
      }
    },
    {
      "id": 4,
      "url": "http://source.unsplash.com/random/4",
      "user": {
        "name": "cardi B"
      }
    },
    {
      "id": 5,
      "url": "http://source.unsplash.com/random/5",
      "user": {
        "name": "john"
      }
    },
    {
      "id": 6,
      "url": "http://source.unsplash.com/random/6",
      "user": {
        "name": "tega"
      }
    },
    {
      "id": 7,
      "url": "http://source.unsplash.com/random/7",
      "user": {
        "name": "hilton"
      }
    },
    {
      "id": 8,
      "url": "http://source.unsplash.com/random/8",
      "user": {
        "name": "admin"
      }
    },
    {
      "id": 9,
      "url": "http://source.unsplash.com/random/9",
      "user": {
        "name": "john"
      }
    },
    {
      "id": 10,
      "url": "http://source.unsplash.com/random/10",
      "user": {
        "name": "cardi B"
      }
    },
    {
      "id": 11,
      "url": "http://source.unsplash.com/random/11",
      "user": {
        "name": "cardi B"
      }
    },
    {
      "id": 12,
      "url": "http://source.unsplash.com/random/12",
      "user": {
        "name": "cardi B"
      }
    },
    {
      "id": 13,
      "url": "http://source.unsplash.com/random/13",
      "user": {
        "name": "admin"
      }
    },
    {
      "id": 14,
      "url": "http://source.unsplash.com/random/14",
      "user": {
        "name": "tega"
      }
    },
    {
      "id": 15,
      "url": "http://source.unsplash.com/random/15",
      "user": {
        "name": "tega"
      }
    },
    {
      "id": 16,
      "url": "http://source.unsplash.com/random/16",
      "user": {
        "name": "cardi B"
      }
    },
    {
      "id": 17,
      "url": "http://source.unsplash.com/random/17",
      "user": {
        "name": "cardi B"
      }
    },
    {
      "id": 18,
      "url": "http://source.unsplash.com/random/18",
      "user": {
        "name": "admin"
      }
    },
    {
      "id": 19,
      "url": "http://source.unsplash.com/random/19",
      "user": {
        "name": "tega"
      }
    },
    {
      "id": 20,
      "url": "http://source.unsplash.com/random/20",
      "user": {
        "name": "hilton"
      }
    },
    {
      "id": 21,
      "url": "http://source.unsplash.com/random/21",
      "user": {
        "name": "admin"
      }
    },
    {
      "id": 22,
      "url": "http://source.unsplash.com/random/22",
      "user": {
        "name": "tega"
      }
    },
    {
      "id": 23,
      "url": "http://source.unsplash.com/random/23",
      "user": {
        "name": "hilton"
      }
    },
    {
      "id": 24,
      "url": "http://source.unsplash.com/random/24",
      "user": {
        "name": "tega"
      }
    },
    {
      "id": 25,
      "url": "http://source.unsplash.com/random/25",
      "user": {
        "name": "hilton"
      }
    },
    {
      "id": 26,
      "url": "http://source.unsplash.com/random/26",
      "user": {
        "name": "tega"
      }
    },
    {
      "id": 27,
      "url": "http://source.unsplash.com/random/27",
      "user": {
        "name": "hilton"
      }
    },
    {
      "id": 28,
      "url": "http://source.unsplash.com/random/28",
      "user": {
        "name": "admin"
      }
    },
    {
      "id": 29,
      "url": "http://source.unsplash.com/random/29",
      "user": {
        "name": "tega"
      }
    },
    {
      "id": 30,
      "url": "http://source.unsplash.com/random/30",
      "user": {
        "name": "john"
      }
    },
    {
      "id": 31,
      "url": "http://source.unsplash.com/random/31",
      "user": {
        "name": "hilton"
      }
    },
    {
      "id": 32,
      "url": "http://source.unsplash.com/random/32",
      "user": {
        "name": "admin"
      }
    },
    {
      "id": 33,
      "url": "http://source.unsplash.com/random/33",
      "user": {
        "name": "john"
      }
    },
    {
      "id": 34,
      "url": "http://source.unsplash.com/random/34",
      "user": {
        "name": "tega"
      }
    },
    {
      "id": 35,
      "url": "http://source.unsplash.com/random/35",
      "user": {
        "name": "admin"
      }
    },
    {
      "id": 36,
      "url": "http://source.unsplash.com/random/36",
      "user": {
        "name": "john"
      }
    },
    {
      "id": 37,
      "url": "http://source.unsplash.com/random/37",
      "user": {
        "name": "cardi B"
      }
    },
    {
      "id": 38,
      "url": "http://source.unsplash.com/random/38",
      "user": {
        "name": "cardi B"
      }
    },
    {
      "id": 39,
      "url": "http://source.unsplash.com/random/39",
      "user": {
        "name": "hilton"
      }
    },
    {
      "id": 40,
      "url": "http://source.unsplash.com/random/40",
      "user": {
        "name": "admin"
      }
    },
    {
      "id": 41,
      "url": "http://source.unsplash.com/random/41",
      "user": {
        "name": "hilton"
      }
    },
    {
      "id": 42,
      "url": "http://source.unsplash.com/random/42",
      "user": {
        "name": "hilton"
      }
    },
    {
      "id": 43,
      "url": "http://source.unsplash.com/random/43",
      "user": {
        "name": "hilton"
      }
    },
    {
      "id": 44,
      "url": "http://source.unsplash.com/random/44",
      "user": {
        "name": "admin"
      }
    },
    {
      "id": 45,
      "url": "http://source.unsplash.com/random/45",
      "user": {
        "name": "tega"
      }
    },
    {
      "id": 46,
      "url": "http://source.unsplash.com/random/46",
      "user": {
        "name": "tega"
      }
    },
    {
      "id": 47,
      "url": "http://source.unsplash.com/random/47",
      "user": {
        "name": "cardi B"
      }
    },
    {
      "id": 48,
      "url": "http://source.unsplash.com/random/48",
      "user": {
        "name": "cardi B"
      }
    },
    {
      "id": 49,
      "url": "http://source.unsplash.com/random/49",
      "user": {
        "name": "cardi B"
      }
    },
    {
      "id": 50,
      "url": "http://source.unsplash.com/random/50",
      "user": {
        "name": "cardi B"
      }
    },
    {
      "id": 51,
      "url": "http://source.unsplash.com/random/51",
      "user": {
        "name": "hilton"
      }
    },
    {
      "id": 52,
      "url": "http://source.unsplash.com/random/52",
      "user": {
        "name": "cardi B"
      }
    },
    {
      "id": 53,
      "url": "http://source.unsplash.com/random/53",
      "user": {
        "name": "cardi B"
      }
    },
    {
      "id": 54,
      "url": "http://source.unsplash.com/random/54",
      "user": {
        "name": "admin"
      }
    },
    {
      "id": 55,
      "url": "http://source.unsplash.com/random/55",
      "user": {
        "name": "john"
      }
    },
    {
      "id": 56,
      "url": "http://source.unsplash.com/random/56",
      "user": {
        "name": "cardi B"
      }
    },
    {
      "id": 57,
      "url": "http://source.unsplash.com/random/57",
      "user": {
        "name": "admin"
      }
    },
    {
      "id": 58,
      "url": "http://source.unsplash.com/random/58",
      "user": {
        "name": "hilton"
      }
    },
    {
      "id": 59,
      "url": "http://source.unsplash.com/random/59",
      "user": {
        "name": "admin"
      }
    },
    {
      "id": 60,
      "url": "http://source.unsplash.com/random/60",
      "user": {
        "name": "hilton"
      }
    },
    {
      "id": 61,
      "url": "http://source.unsplash.com/random/61",
      "user": {
        "name": "cardi B"
      }
    },
    {
      "id": 62,
      "url": "http://source.unsplash.com/random/62",
      "user": {
        "name": "john"
      }
    },
    {
      "id": 63,
      "url": "http://source.unsplash.com/random/63",
      "user": {
        "name": "john"
      }
    },
    {
      "id": 64,
      "url": "http://source.unsplash.com/random/64",
      "user": {
        "name": "john"
      }
    },
    {
      "id": 65,
      "url": "http://source.unsplash.com/random/65",
      "user": {
        "name": "tega"
      }
    },
    {
      "id": 66,
      "url": "http://source.unsplash.com/random/66",
      "user": {
        "name": "tega"
      }
    },
    {
      "id": 67,
      "url": "http://source.unsplash.com/random/67",
      "user": {
        "name": "admin"
      }
    },
    {
      "id": 68,
      "url": "http://source.unsplash.com/random/68",
      "user": {
        "name": "cardi B"
      }
    },
    {
      "id": 69,
      "url": "http://source.unsplash.com/random/69",
      "user": {
        "name": "admin"
      }
    },
    {
      "id": 70,
      "url": "http://source.unsplash.com/random/70",
      "user": {
        "name": "tega"
      }
    },
    {
      "id": 71,
      "url": "http://source.unsplash.com/random/71",
      "user": {
        "name": "admin"
      }
    },
    {
      "id": 72,
      "url": "http://source.unsplash.com/random/72",
      "user": {
        "name": "cardi B"
      }
    },
    {
      "id": 73,
      "url": "http://source.unsplash.com/random/73",
      "user": {
        "name": "cardi B"
      }
    },
    {
      "id": 74,
      "url": "http://source.unsplash.com/random/74",
      "user": {
        "name": "admin"
      }
    },
    {
      "id": 75,
      "url": "http://source.unsplash.com/random/75",
      "user": {
        "name": "cardi B"
      }
    },
    {
      "id": 76,
      "url": "http://source.unsplash.com/random/76",
      "user": {
        "name": "cardi B"
      }
    },
    {
      "id": 77,
      "url": "http://source.unsplash.com/random/77",
      "user": {
        "name": "hilton"
      }
    },
    {
      "id": 78,
      "url": "http://source.unsplash.com/random/78",
      "user": {
        "name": "admin"
      }
    },
    {
      "id": 79,
      "url": "http://source.unsplash.com/random/79",
      "user": {
        "name": "tega"
      }
    },
    {
      "id": 80,
      "url": "http://source.unsplash.com/random/80",
      "user": {
        "name": "admin"
      }
    },
    {
      "id": 81,
      "url": "http://source.unsplash.com/random/81",
      "user": {
        "name": "hilton"
      }
    },
    {
      "id": 82,
      "url": "http://source.unsplash.com/random/82",
      "user": {
        "name": "hilton"
      }
    },
    {
      "id": 83,
      "url": "http://source.unsplash.com/random/83",
      "user": {
        "name": "cardi B"
      }
    },
    {
      "id": 84,
      "url": "http://source.unsplash.com/random/84",
      "user": {
        "name": "admin"
      }
    },
    {
      "id": 85,
      "url": "http://source.unsplash.com/random/85",
      "user": {
        "name": "tega"
      }
    },
    {
      "id": 86,
      "url": "http://source.unsplash.com/random/86",
      "user": {
        "name": "cardi B"
      }
    },
    {
      "id": 87,
      "url": "http://source.unsplash.com/random/87",
      "user": {
        "name": "cardi B"
      }
    },
    {
      "id": 88,
      "url": "http://source.unsplash.com/random/88",
      "user": {
        "name": "john"
      }
    },
    {
      "id": 89,
      "url": "http://source.unsplash.com/random/89",
      "user": {
        "name": "cardi B"
      }
    },
    {
      "id": 90,
      "url": "http://source.unsplash.com/random/90",
      "user": {
        "name": "john"
      }
    },
    {
      "id": 91,
      "url": "http://source.unsplash.com/random/91",
      "user": {
        "name": "admin"
      }
    },
    {
      "id": 92,
      "url": "http://source.unsplash.com/random/92",
      "user": {
        "name": "cardi B"
      }
    },
    {
      "id": 93,
      "url": "http://source.unsplash.com/random/93",
      "user": {
        "name": "john"
      }
    },
    {
      "id": 94,
      "url": "http://source.unsplash.com/random/94",
      "user": {
        "name": "cardi B"
      }
    },
    {
      "id": 95,
      "url": "http://source.unsplash.com/random/95",
      "user": {
        "name": "cardi B"
      }
    },
    {
      "id": 96,
      "url": "http://source.unsplash.com/random/96",
      "user": {
        "name": "john"
      }
    },
    {
      "id": 97,
      "url": "http://source.unsplash.com/random/97",
      "user": {
        "name": "john"
      }
    },
    {
      "id": 98,
      "url": "http://source.unsplash.com/random/98",
      "user": {
        "name": "cardi B"
      }
    },
    {
      "id": 99,
      "url": "http://source.unsplash.com/random/99",
      "user": {
        "name": "tega"
      }
    },
    {
      "id": 100,
      "url": "http://source.unsplash.com/random/100",
      "user": {
        "name": "admin"
      }
    }
  ],
  "users": [
    {
      "name": "admin"
    },
    {
      "name": "tega"
    },
    {
      "name": "hilton"
    },
    {
      "name": "john"
    },
    {
      "name": "cardi B"
    }
  ]
}